rebello/__init__.py
rebello/cli.py
rebello/diff.py
rebello/diff_test.py
rebello/edi.py
rebello/edi_test.py
rebello/md.py
rebello/md_test.py
rebello/models.py
rebello/py.typed
rebello/settings.py
rebello/trello.py
rebello/trello_test.py
rebello/md_test_files/malformed/empty.md
rebello/md_test_files/malformed/no_board_id.md
rebello/md_test_files/malformed/no_list_id.md
rebello/md_test_files/pairs/created_card.md
rebello/md_test_files/pairs/created_card.py
rebello/md_test_files/pairs/no_cols.md
rebello/md_test_files/pairs/no_cols.py
rebello/md_test_files/pairs/one_of_everything.md
rebello/md_test_files/pairs/one_of_everything.py
rebello/md_test_files/pairs/simple_kanban.md
rebello/md_test_files/pairs/simple_kanban.py
rebello/trello_responses/README.md
rebello/trello_responses/board.json
rebello/trello_responses/boards.json
rebello/trello_responses/cards.json
rebello/trello_responses/lists.json
rebello-0.2.0.dist-info/METADATA
rebello-0.2.0.dist-info/WHEEL
rebello-0.2.0.dist-info/entry_points.txt
rebello-0.2.0.dist-info/licenses/LICENSE
rebello-0.2.0.dist-info/RECORD
