Metadata-Version: 2.4
Name: rebello
Version: 0.2.0
Summary: Editor-driven Markdown interface for Trello
Project-URL: homepage, https://github.com/alexjuda/rebello
Author-email: alexjuda <alexanderjuda@gmail.com>
License-Expression: Apache-2.0
License-File: LICENSE
Requires-Python: >=3.12
Requires-Dist: aiohttp>=3.12.15
Requires-Dist: pydantic-settings>=2.10.1
